livekit/plugins/tenvad/__init__.py
livekit/plugins/tenvad/log.py
livekit/plugins/tenvad/onnx_model.py
livekit/plugins/tenvad/py.typed
livekit/plugins/tenvad/vad.py
livekit/plugins/tenvad/version.py
livekit/plugins/tenvad/prebuilt/Linux/x64/libten_vad
livekit/plugins/tenvad/prebuilt/Windows/x64/ten_vad.dll
livekit/plugins/tenvad/prebuilt/Windows/x64/ten_vad.lib
livekit/plugins/tenvad/prebuilt/Windows/x86/ten_vad.dll
livekit/plugins/tenvad/prebuilt/Windows/x86/ten_vad.lib
livekit/plugins/tenvad/prebuilt/macOS/ten_vad.framework/ten_vad
livekit/plugins/tenvad/prebuilt/macOS/ten_vad.framework/Headers/ten_vad.h
livekit/plugins/tenvad/prebuilt/macOS/ten_vad.framework/Resources/Info.plist
livekit/plugins/tenvad/prebuilt/macOS/ten_vad.framework/Versions/A/ten_vad
livekit_plugins_tenvad-1.0.8.dist-info/METADATA
livekit_plugins_tenvad-1.0.8.dist-info/WHEEL
livekit_plugins_tenvad-1.0.8.dist-info/licenses/LICENSE
livekit_plugins_tenvad-1.0.8.dist-info/RECORD
