Metadata-Version: 2.4
Name: livekit-plugins-tenvad
Version: 1.0.8
Summary: Agent Framework Plugin for TEN VAD
Project-URL: Documentation, https://docs.livekit.io
Project-URL: Website, https://livekit.io/
Project-URL: Source, https://github.com/dangvansam/livekit-plugins-tenvad
Author-email: Sam Dang <dangvansam98@gmail.com>
License-Expression: Apache-2.0
License-File: LICENSE
Keywords: audio,livekit,realtime,video,webrtc
Classifier: Intended Audience :: Developers
Classifier: License :: OSI Approved :: Apache Software License
Classifier: Programming Language :: Python :: 3
Classifier: Programming Language :: Python :: 3 :: Only
Classifier: Programming Language :: Python :: 3.10
Classifier: Programming Language :: Python :: 3.11
Classifier: Topic :: Multimedia :: Sound/Audio
Classifier: Topic :: Multimedia :: Video
Classifier: Topic :: Scientific/Engineering :: Artificial Intelligence
Requires-Python: >=3.10
Requires-Dist: livekit-agents>=1.2.6
Requires-Dist: numpy>=1.26
Requires-Dist: onnxruntime>=1.18
Provides-Extra: test
Requires-Dist: livekit-plugins-silero==1.2.12; extra == 'test'
Requires-Dist: loguru==0.7.3; extra == 'test'
Requires-Dist: matplotlib==3.10.5; extra == 'test'
